LICENSE
MANIFEST.in
README.rst
setup.py
data/linkselect.conf.example
src/linkselect/__init__.py
src/linkselect/core.py
src/linkselect/defs.py
src/linkselect/gui.py
src/linkselect.egg-info/PKG-INFO
src/linkselect.egg-info/SOURCES.txt
src/linkselect.egg-info/dependency_links.txt
src/linkselect.egg-info/entry_points.txt
src/linkselect.egg-info/top_level.txt
src/linkselect.egg-info/zip-safe