Metadata-Version: 1.1
Name: linkselect
Version: 0.0.1-beta1
Summary: Selector of multiple targets for symlinks.
Home-page: https://github.com/beli-sk/linkselect
Author: Michal Belica
Author-email: devel@beli.sk
License: GPL-3
Platform: UNKNOWN
Classifier: Development Status :: 3 - Alpha
Classifier: Environment :: X11 Applications :: Qt
Classifier: Intended Audience :: System Administrators
Classifier: Intended Audience :: Developers
Classifier: License :: OSI Approved :: GNU General Public License v3 or later (GPLv3+)
Classifier: Operating System :: OS Independent
Classifier: Programming Language :: Python :: 3
Classifier: Topic :: Utilities
